pipeful/__init__.py
pipeful-0.0.1.dist-info/licenses/LICENSE
pipeful-0.0.1.dist-info/METADATA
pipeful-0.0.1.dist-info/WHEEL
pipeful-0.0.1.dist-info/top_level.txt
pipeful-0.0.1.dist-info/RECORD
